pytidenetworking/__init__.py
pytidenetworking/client.py
pytidenetworking/connection.py
pytidenetworking/constants.py
pytidenetworking/message.py
pytidenetworking/message_base.py
pytidenetworking/message_relay_filter.py
pytidenetworking/peer.py
pytidenetworking/pending_message.py
pytidenetworking/server.py
pytidenetworking/threading/__init__.py
pytidenetworking/threading/fixedupdatethreads.py
pytidenetworking/transports/__init__.py
pytidenetworking/transports/iclient.py
pytidenetworking/transports/ipeer.py
pytidenetworking/transports/iserver.py
pytidenetworking/transports/tcp/__init__.py
pytidenetworking/transports/tcp/tcp_client.py
pytidenetworking/transports/tcp/tcp_connection.py
pytidenetworking/transports/tcp/tcp_peer.py
pytidenetworking/transports/tcp/tcp_server.py
pytidenetworking/transports/udp/__init__.py
pytidenetworking/transports/udp/udp_client.py
pytidenetworking/transports/udp/udp_connection.py
pytidenetworking/transports/udp/udp_peer.py
pytidenetworking/transports/udp/udp_server.py
pytidenetworking/utils/__init__.py
pytidenetworking/utils/bitfield.py
pytidenetworking/utils/connection_metrics.py
pytidenetworking/utils/converter.py
pytidenetworking/utils/delayed_events.py
pytidenetworking/utils/eventhandler.py
pytidenetworking/utils/exceptions.py
pytidenetworking/utils/helper.py
pytidenetworking/utils/logengine.py
pytidenetworking/utils/notify_sequencer.py
pytidenetworking/utils/object_pool.py
pytidenetworking/utils/relieble_sequencer.py
pytidenetworking/utils/rolling_stat.py
pytidenetworking/utils/sequencer.py
pytide_networking-2.1.0a0.dist-info/LICENSE
pytide_networking-2.1.0a0.dist-info/METADATA
pytide_networking-2.1.0a0.dist-info/WHEEL
pytide_networking-2.1.0a0.dist-info/top_level.txt
pytide_networking-2.1.0a0.dist-info/RECORD
