Metadata-Version: 2.1
Name: pytide-networking
Version: 2.1.0a0
Summary: Python implementation of Riptide
Author-email: ebosseck <pypi-packages@mail-b.org>
Project-URL: homepage, https://github.com/ebosseck/PytideNetworking
Project-URL: repository, https://github.com/ebosseck/PytideNetworking
Keywords: PytideNetworking,networking,Riptide
Classifier: Programming Language :: Python :: 3
Classifier: Development Status :: 3 - Alpha
Classifier: Intended Audience :: Developers
Classifier: License :: OSI Approved :: MIT License
Classifier: Operating System :: OS Independent
Classifier: Topic :: Software Development :: Libraries
Classifier: Topic :: System :: Networking
Requires-Python: >=3.6
License-File: LICENSE
